pocket_ic/__init__.py
pocket_ic/pocket_ic.py
pocket_ic/pocket_ic_server.py
pocket_ic/subnet_config.py
pocket_ic-3.1.1.dist-info/LICENSE
pocket_ic-3.1.1.dist-info/METADATA
pocket_ic-3.1.1.dist-info/WHEEL
pocket_ic-3.1.1.dist-info/RECORD
