Metadata-Version: 2.3
Name: pocket_ic
Version: 3.1.1
Summary: PocketIC: A Canister Smart Contract Testing Platform
License: Apache-2.0
Author: The Internet Computer Project Developers
Author-email: dept-testing_&_verification@dfinity.org
Requires-Python: >=3.10,<4.0
Classifier: License :: OSI Approved :: Apache Software License
Classifier: Programming Language :: Python :: 3
Classifier: Programming Language :: Python :: 3.10
Classifier: Programming Language :: Python :: 3.11
Classifier: Programming Language :: Python :: 3.12
Classifier: Programming Language :: Python :: 3.13
Requires-Dist: ic-py (>=1.0.1,<2.0.0)
Requires-Dist: requests (>=2.31.0,<3.0.0)
Project-URL: Documentation, https://github.com/dfinity/pocketic-py/blob/main/HOWTO.md
Project-URL: Homepage, https://github.com/dfinity/pocketic-py/
